dreams_mc/__init__.py
dreams_mc/make_model_card.py
dreams_mc/assets/.DS_Store
dreams_mc/assets/__pycache__/config.cpython-310.pyc
dreams_mc/assets/css/color-blue.css
dreams_mc/assets/css/color-brown.css
dreams_mc/assets/css/color-cyan.css
dreams_mc/assets/css/color-green.css
dreams_mc/assets/css/color-indigo.css
dreams_mc/assets/css/color-orange.css
dreams_mc/assets/css/color-purple.css
dreams_mc/assets/css/color-red.css
dreams_mc/assets/css/color-teal.css
dreams_mc/assets/css/color-yellow.css
dreams_mc/assets/css/stylesheet.css
dreams_mc/assets/js/theme.js
dreams_mc/assets/sasss/_elements.scss
dreams_mc/assets/sasss/_extras.scss
dreams_mc/assets/sasss/_footer.scss
dreams_mc/assets/sasss/_header.scss
dreams_mc/assets/sasss/_helpers.scss
dreams_mc/assets/sasss/_layouts.scss
dreams_mc/assets/sasss/_mixins.scss
dreams_mc/assets/sasss/_reset.scss
dreams_mc/assets/sasss/_variables.scss
dreams_mc/assets/sasss/color-blue.scss
dreams_mc/assets/sasss/color-brown.scss
dreams_mc/assets/sasss/color-cyan.scss
dreams_mc/assets/sasss/color-green.scss
dreams_mc/assets/sasss/color-indigo.scss
dreams_mc/assets/sasss/color-orange.scss
dreams_mc/assets/sasss/color-purple.scss
dreams_mc/assets/sasss/color-red.scss
dreams_mc/assets/sasss/color-teal.scss
dreams_mc/assets/sasss/color-yellow.scss
dreams_mc/assets/sasss/stylesheet.scss
dreams_mc/assets/sasss/bootstrap/_alert.scss
dreams_mc/assets/sasss/bootstrap/_badge.scss
dreams_mc/assets/sasss/bootstrap/_breadcrumb.scss
dreams_mc/assets/sasss/bootstrap/_button-group.scss
dreams_mc/assets/sasss/bootstrap/_buttons.scss
dreams_mc/assets/sasss/bootstrap/_card.scss
dreams_mc/assets/sasss/bootstrap/_carousel.scss
dreams_mc/assets/sasss/bootstrap/_close.scss
dreams_mc/assets/sasss/bootstrap/_code.scss
dreams_mc/assets/sasss/bootstrap/_custom-forms.scss
dreams_mc/assets/sasss/bootstrap/_dropdown.scss
dreams_mc/assets/sasss/bootstrap/_forms.scss
dreams_mc/assets/sasss/bootstrap/_functions.scss
dreams_mc/assets/sasss/bootstrap/_grid.scss
dreams_mc-0.0.3.dist-info/AUTHORS.rst
dreams_mc-0.0.3.dist-info/LICENSE.txt
dreams_mc-0.0.3.dist-info/METADATA
dreams_mc-0.0.3.dist-info/WHEEL
dreams_mc-0.0.3.dist-info/entry_points.txt
dreams_mc-0.0.3.dist-info/top_level.txt
dreams_mc-0.0.3.dist-info/RECORD
