Metadata-Version: 2.1
Name: dreams-mc
Version: 0.0.3
Summary: Library for DL models reporting. dreams_mc is a Python package designed to simplify the process of creating comprehensive model cards for deep learning models. Model cards(mc) are crucial for documenting the performance, usage, and limitations of AI models, promoting transparency and ethical use of AI.
Home-page: https://github.com/LucidJun/DREAM
Author: LucidMoon
Classifier: Programming Language :: Python :: 3
Classifier: License :: OSI Approved :: BSD License
Classifier: Operating System :: OS Independent
License-File: LICENSE.txt
License-File: AUTHORS.rst
Requires-Dist: PyYAML ==6.0.1
Requires-Dist: sphinx-rtd-theme
